{"b":"PSA","c":87,"lang":"heb","verses":[{"v":1,"words":[{"w":"לִבְנֵי־","st":"H1121","tr":"liv·nei-","cx":"for the sons"},{"w":"קֹ֭רַח","st":"H7141","tr":"Ko·rach","cx":"of Korah"},{"w":"מִזְמ֣וֹר","st":"H4210","tr":"miz·Mor","cx":"A Psalm"},{"w":"שִׁ֑יר","st":"H7892","tr":"Shir;","cx":"[or] Song"},{"w":"יְ֝סוּדָת֗וֹ","st":"H3248","tr":"ye·su·da·To,","cx":"His foundation"},{"w":"בְּהַרְרֵי־","st":"H2042","tr":"be·har·rei-","cx":"mountains"},{"w":"קֹֽדֶשׁ׃","st":"H6944","tr":"Ko·desh.","cx":"[is] in the holy"}]},{"v":2,"words":[{"w":"אֹהֵ֣ב","st":"H157","tr":"'o·Hev","cx":"loveth"},{"w":"יְ֭הוָה","st":"H3068","tr":"Yah·weh","cx":"The LORD"},{"w":"שַׁעֲרֵ֣י","st":"H8179","tr":"sha·'a·Rei","cx":"the gates"},{"w":"צִיּ֑וֹן","st":"H6726","tr":"tzi·Yon;","cx":"of Zion"},{"w":"מִ֝כֹּ֗ל","st":"H3605","tr":"mik·Kol,","cx":"all"},{"w":"מִשְׁכְּנ֥וֹת","st":"H4908","tr":"mish·ke·Not","cx":"more than all the dwellings"},{"w":"יַעֲקֹֽב׃","st":"H3290","tr":"ya·'a·Ko.","cx":"of Jacob"}]},{"v":3,"words":[{"w":"נִ֭כְבָּדוֹת","st":"H3513","tr":"Nich·ba·dot","cx":"Glorious things"},{"w":"מְדֻבָּ֣ר","st":"H1696","tr":"me·dub·Bar","cx":"are spoken"},{"w":"בָּ֑ךְ","st":"H0","tr":"Bach;"},{"w":"עִ֖יר","st":"H5892","tr":"'ir","cx":"of thee O city"},{"w":"הָאֱלֹהִ֣ים","st":"H430","tr":"ha·'E·lo·Him","cx":"of God"},{"w":"סֶֽלָה׃","st":"H5542","tr":"Se·lah.","cx":"Selah"}]},{"v":4,"words":[{"w":"אַזְכִּ֤יר ׀","st":"H2142","tr":"'az·Kir","cx":"I will make mention"},{"w":"רַ֥הַב","st":"H7294","tr":"Ra·hav","cx":"of Rahab"},{"w":"וּבָבֶ֗ל","st":"H894","tr":"u·va·Vel,","cx":"and Babylon"},{"w":"לְֽיֹ֫דְעָ֥י","st":"H3045","tr":"le·Yo·de·'Ai","cx":"to them that know"},{"w":"הִנֵּ֤ה","st":"H2009","tr":"hin·Neh","cx":"Behold"},{"w":"פְלֶ֣שֶׁת","st":"H6429","tr":"fe·Le·shet","cx":"me behold Philistia"},{"w":"וְצ֣וֹר","st":"H6865","tr":"ve·Tzor","cx":"and Tyre"},{"w":"עִם־","st":"H5973","tr":"'im-","cx":"with"},{"w":"כּ֑וּשׁ","st":"H3568","tr":"Kush;","cx":"with Ethiopia"},{"w":"זֶ֝֗ה","st":"H2088","tr":"Zeh,","cx":"This"},{"w":"יֻלַּד־","st":"H3205","tr":"yul·lad-","cx":"this [man] was born"},{"w":"שָֽׁם׃","st":"H8033","tr":"Sham.","cx":"But"}]},{"v":5,"words":[{"w":"וּֽלֲצִיּ֨וֹן ׀","st":"H6726","tr":"u·la·tzi·Yon","cx":"And of Zion"},{"w":"יֵאָמַ֗ר","st":"H559","tr":"ye·'a·Mar,","cx":"it shall be said"},{"w":"אִ֣ישׁ","st":"H376","tr":"'ish","cx":"This and that man"},{"w":"וְ֭אִישׁ","st":"H376","tr":"Ve·'ish","cx":"one"},{"w":"יֻלַּד־","st":"H3205","tr":"yul·lad-","cx":"was born"},{"w":"בָּ֑הּ","st":"H0","tr":"Bah;"},{"w":"וְה֖וּא","st":"H1931","tr":"ve·Hu","cx":"Himself"},{"w":"יְכוֹנְנֶ֣הָ","st":"H3559","tr":"ye·chon·Ne·ha","cx":"himself shall establish"},{"w":"עֶלְיֽוֹן׃","st":"H5945","tr":"el·Yon.","cx":"in her and the highest"}]},{"v":6,"words":[{"w":"יְֽהוָ֗ה","st":"H3068","tr":"Yah·weh","cx":"The LORD"},{"w":"יִ֭סְפֹּר","st":"H5608","tr":"Yis·por","cx":"shall count"},{"w":"בִּכְת֣וֹב","st":"H3789","tr":"bich·Tov","cx":"when he writeth up"},{"w":"עַמִּ֑ים","st":"H5971","tr":"'am·Mim;","cx":"the people"},{"w":"זֶ֖ה","st":"H2088","tr":"zeh","cx":"This"},{"w":"יֻלַּד־","st":"H3205","tr":"yul·lad-","cx":"[that] this [man] was born"},{"w":"שָׁ֣ם","st":"H8033","tr":"sham","cx":"there"},{"w":"סֶֽלָה׃","st":"H5542","tr":"Se·lah.","cx":"there Selah"}]},{"v":7,"words":[{"w":"וְשָׁרִ֥ים","st":"H7891","tr":"ve·sha·Rim","cx":"As well the singers"},{"w":"כְּחֹלְלִ֑ים","st":"H2490","tr":"ke·cho·le·Lim;","cx":"as the players"},{"w":"כָּֽל־","st":"H3605","tr":"kal-","cx":"All"},{"w":"מַעְיָנַ֥י","st":"H4599","tr":"ma'·ya·Nai","cx":"on instruments [shall be there] all my springs"},{"w":"בָּֽךְ׃","st":"H0","tr":"Bach."}]}]}